tesbml-5.18.1.2.data/purelib/tesbml/__init__.py
tesbml-5.18.1.2.data/purelib/tesbml/_libsbml.so
tesbml-5.18.1.2.data/purelib/tesbml/libsbml.py
tesbml-5.18.1.2.dist-info/METADATA
tesbml-5.18.1.2.dist-info/WHEEL
tesbml-5.18.1.2.dist-info/top_level.txt
tesbml-5.18.1.2.dist-info/RECORD
