Metadata-Version: 2.1
Name: tesbml
Version: 5.18.1.2
Summary: LibSBML Python API
Home-page: http://sbml.org
Author: SBML Team
Author-email: libsbml-team@googlegroups.com
License: LGPL
Platform: UNKNOWN
Classifier: Intended Audience :: Science/Research
Classifier: Operating System :: MacOS :: MacOS X
Classifier: Operating System :: Microsoft :: Windows
Classifier: Operating System :: POSIX
Classifier: Programming Language :: C++
